localpython/__main__.py
localpython-0.2.0.dist-info/licenses/LICENSE
localpython-0.2.0.dist-info/METADATA
localpython-0.2.0.dist-info/WHEEL
localpython-0.2.0.dist-info/entry_points.txt
localpython-0.2.0.dist-info/top_level.txt
localpython-0.2.0.dist-info/RECORD
