Metadata-Version: 2.4
Name: localpython
Version: 0.2.0
Summary: Run Python scripts using the local virtual environment without activating it
Author-email: Yali Achitov <yaliachitov26@gmail.com>
Requires-Python: >=3.7
License-File: LICENSE
Dynamic: license-file
